{
  "events": [
    {
      "id": "1",
      "title": "test event",
      "startTime": 1568928644,
      "endTime": 1568928644,
      "location": "somewhere",
      "assignee": "wangweiyi722@gmail.com",
      "contacts": [
        "wangweiyi722@gmail.com"
      ]
    },
    {
      "id": "2",
      "title": "test event2",
      "startTime": 1568928644,
      "endTime": 1568928644,
      "location": "somewhere2",
      "assignee": "wangweiyi722@gmail.com",
      "contacts": [
        "wangweiyi722@gmail.com"
      ]
    },
    {
      "title": "event create test 1",
      "startTime": 123456789123,
      "endTime": 123456789123,
      "location": "abcdef",
      "contacts": [
        "wangweiyi722@gmail.com"
      ],
      "assignee": "wangweiyi722@gmail.com",
      "id": "V0S91_3"
    },
    {
      "title": "test history",
      "startTime": 1928329819,
      "endTime": 1928938198,
      "location": "aonaonw",
      "contacts": [
        "wangweiyi722@gmail.com"
      ],
      "assignee": "wangweiyi722@gmail.com",
      "id": "l0qWS8a"
    },
    {
      "title": "test event create 6",
      "startTime": 1234567819,
      "endTime": 1829347919,
      "location": "abcdef",
      "assignee": "wangweiyi722@gmail.com",
      "contacts": [
        "wangweiyi722@gmail.com"
      ],
      "id": "GeW02A7"
    },
    {
      "title": "test event create 7",
      "startTime": 1928329819,
      "endTime": 1928329819,
      "location": "somewhere 2",
      "assignee": "wangweiyi722@gmail.com",
      "contacts": [
        "wangweiyi722@gmail.com"
      ],
      "id": "9-nulla"
    },
    {
      "title": "test event create 7 numbers",
      "startTime": 1928329819,
      "endTime": 1928938198,
      "location": "abcdef",
      "assignee": "wangweiyi722@gmail.com",
      "contacts": [
        "wangweiyi722@gmail.com"
      ],
      "id": "4YxUVNl"
    },
    {
      "title": "test event create 8 numbers",
      "startTime": 1928329819,
      "endTime": 1928329819,
      "location": "aonaonw",
      "assignee": "wangweiyi722@gmail.com",
      "contacts": [
        "wangweiyi722@gmail.com"
      ],
      "id": "0f4idNq"
    }
  ],
  "tasks": [
    {
      "description": "task1",
      "deadline": 1568928644,
      "assignee": "someone@example.com",
      "eventId": "1",
      "completed": false,
      "id": "1",
      "comments": []
    },
    {
      "description": "task2",
      "deadline": 1568928644,
      "assignee": "someone@example.com",
      "completed": true,
      "eventId": "1",
      "id": "2",
      "comments": []
    },
    {
      "id": "3",
      "description": "task3",
      "deadline": 1568928644,
      "assignee": "someone@example.com",
      "completed": false,
      "eventId": "2",
      "comments": []
    },
    {
      "id": "4",
      "description": "task4",
      "deadline": 1568928644,
      "assignee": "someone@example.com",
      "completed": false,
      "eventId": "2",
      "comments": []
    },
    {
      "description": "fewf",
      "deadline": 1234251,
      "assignee": "wawin@maoinw.com",
      "eventId": "1",
      "completed": false,
      "id": "pwB6X4A",
      "comments": []
    },
    {
      "description": "test create 1",
      "deadline": 1234251,
      "assignee": "wawin@maoinw.com",
      "eventId": "1",
      "completed": false,
      "id": "pU-FZRz"
    },
    {
      "description": "test create 2",
      "deadline": 198293849,
      "assignee": "wangweiyi722@gmail.com",
      "eventId": "1",
      "completed": false,
      "id": "fH0EhZ2"
    },
    {
      "description": "test create 3",
      "deadline": 123492829,
      "assignee": "wangweiyi722@gmail.com",
      "eventId": "1",
      "completed": true,
      "id": "BTSdX1o"
    },
    {
      "description": "test create 4",
      "deadline": 123412341,
      "assignee": "wangweiyi722@gmail.com",
      "eventId": "1",
      "completed": false,
      "id": "kcKvCE3"
    },
    {
      "description": "test create 5",
      "deadline": 1234928292,
      "assignee": "wangweiyi722@gmail.com",
      "eventId": "1",
      "completed": false,
      "id": "SDrDxy7"
    },
    {
      "description": "event 2 test create 1",
      "deadline": 12923892,
      "assignee": "wangweiyi722@gmail.com",
      "eventId": "2",
      "completed": false,
      "id": "G5zDUED"
    },
    {
      "description": "event 2 test create 1",
      "deadline": 204971009234,
      "assignee": "wangweiyi722@gmail.com",
      "eventId": "1",
      "completed": true,
      "id": "kGJdi4r"
    },
    {
      "description": "test create 6",
      "deadline": 1234251,
      "assignee": "wawin@maoinw.com",
      "eventId": "2",
      "completed": false,
      "id": "NNtnngU"
    }
  ]
}
